funcnodes_storage/__init__.py
funcnodes_storage/sql/__init__.py
funcnodes_storage/sql/q_builder.py
funcnodes_storage-0.3.0.dist-info/licenses/LICENSE
funcnodes_storage-0.3.0.dist-info/METADATA
funcnodes_storage-0.3.0.dist-info/WHEEL
funcnodes_storage-0.3.0.dist-info/entry_points.txt
funcnodes_storage-0.3.0.dist-info/top_level.txt
funcnodes_storage-0.3.0.dist-info/RECORD
