Metadata-Version: 2.4
Name: funcnodes-storage
Version: 0.3.0
Summary: Interact with local storage like sqlite
License: AGPL-3.0
Classifier: License :: OSI Approved :: GNU Affero General Public License v3 or later (AGPLv3+)
Classifier: Programming Language :: Python :: 3
Requires-Python: >=3.11
License-File: LICENSE
Requires-Dist: funcnodes
Requires-Dist: funcnodes-files
Requires-Dist: aiosqlite<0.21.0,>=0.20.0
Dynamic: license-file
